{
  "CultureText": "Γλώσσα",
  "Delay": "Καθυστέρηση",
  "EditSources": "Επεξεργασία πηγών...",
  "General": "Γενικά",
  "InstallPlugin": "Εγκατάσταση πρόσθετου...",
  "LoadedPlugins": "Φορτωμένα πρόσθετου",
  "Nicknames": "παρωνύμιο",
  "NoPlugins": "Δεν φορτώθηκαν πρόσθετα",
  "NoPluginSensorsHelpText": "Δεν βρέθηκαν αισθητήρες από το πρόσθετο. Βεβαιωθείτε ότι το πρόσθετο είναι ενεργοποιημένο στο παράθυρο πηγών αισθητήρων και ότι έχει εκτελεστεί ανανέωση.",
  "NotifyForUpdate": "Ειδοποίηση για ενημέρωση κατά την εκκίνηση",
  "OriginalName": "Αρχικό όνομα: {0}",
  "Plugins": "Πρόσθετα",
  "PluginSensors": "Πρόσθετοι αισθητήρες",
  "SecondUnit": "sec",
  "SelectSensorNickname": "Επέλεξε έναν αισθητήρα για του βάλεις παρωνύμιο",
  "SensorNickname": "παρωνύμιο αισθητήρα (επεξεργάσιμο)",
  "Sensors": "Αισθητήρες",
  "StartMinimized": "Ελαχιστοποίηση στη Γραμμή Εργασιών κατά την εκκίνηση",
  "StartUserLogon": "Εκκίνηση με την είσοδο του χρήστη",
  "Symbol": "Συμβολισμός",
  "TaskSchedulerAdminRequired": "Δεν ήταν δυνατή η ρύθμιση του προγράμματος ώστε να ξεκινά με τον προγραμματιστή εργασιών των Windows. Απαιτoύνται δικαιώματα διαχειριστή."
}